LICENSE.txt
README.md
setup.cfg
setup.py
ulm/__init__.py
ulm.egg-info/PKG-INFO
ulm.egg-info/SOURCES.txt
ulm.egg-info/dependency_links.txt
ulm.egg-info/top_level.txt