Metadata-Version: 2.1
Name: ulm
Version: 0.0.1
Summary: Best Recommendation Library
Home-page: https://github.com/daun4168/ulm
Download-URL: https://github.com/daun4168/ulm/archive/v0.0.1.tar.gz
Author: Daun Jeong
Author-email: daun.jeong@navercorp.com
License: MIT
Keywords: Recommendation,Machine Learning
Platform: UNKNOWN
Classifier: Development Status :: 3 - Alpha
Classifier: Intended Audience :: Developers
Classifier: License :: OSI Approved :: MIT License
Classifier: Programming Language :: Python :: 3
Classifier: Programming Language :: Python :: 3.9
License-File: LICENSE.txt
